friendlypics/__init__.py
friendlypics/file_object.py
friendlypics/manifest_file.py
friendlypics/version.py
friendlypics/scripts/__init__.py
friendlypics/scripts/fpics.py
friendlypics-0.0.1.dist-info/LICENSE
friendlypics-0.0.1.dist-info/METADATA
friendlypics-0.0.1.dist-info/WHEEL
friendlypics-0.0.1.dist-info/entry_points.txt
friendlypics-0.0.1.dist-info/top_level.txt
friendlypics-0.0.1.dist-info/RECORD
