Metadata-Version: 2.1
Name: friendlypics
Version: 0.0.1
Summary: User friendly command line image manipulation program
Home-page: https://github.com/TheFriendlyCoder/friendlypics
Author: Kevin S. Phillips
Author-email: thefriendlycoder@gmail.com
License: Apache License 2.0
Keywords: image process picture organizer
Platform: UNKNOWN
Classifier: Development Status :: 3 - Alpha
Classifier: Environment :: Console
Classifier: License :: OSI Approved :: Apache Software License
Classifier: Natural Language :: English
Classifier: Operating System :: OS Independent
Classifier: Programming Language :: Python :: 3
Requires-Python: >=3.6.0
Requires-Dist: click
Requires-Dist: pillow
Requires-Dist: piexif
Provides-Extra: dev
Requires-Dist: pytest ; extra == 'dev'
Requires-Dist: pytest-timeout ; extra == 'dev'
Requires-Dist: mock ; extra == 'dev'
Requires-Dist: pylint ; extra == 'dev'
Requires-Dist: tox ; extra == 'dev'
Requires-Dist: tox-factor ; extra == 'dev'
